odoo10_addon_website_sale_show_company_data-10.0.1.0.0.99.dev5-py3.8-nspkg.pth
odoo/addons/website_sale_show_company_data/README.rst
odoo/addons/website_sale_show_company_data/__init__.py
odoo/addons/website_sale_show_company_data/__manifest__.py
odoo/addons/website_sale_show_company_data/i18n/website_sale_show_company_data.pot
odoo/addons/website_sale_show_company_data/readme/CONFIGURATION.rst
odoo/addons/website_sale_show_company_data/readme/CONTRIBUTORS.rst
odoo/addons/website_sale_show_company_data/readme/DESCRIPTION.rst
odoo/addons/website_sale_show_company_data/readme/USAGE.rst
odoo/addons/website_sale_show_company_data/static/description/icon.png
odoo/addons/website_sale_show_company_data/static/description/index.html
odoo/addons/website_sale_show_company_data/views/website_sale_address.xml
odoo10_addon_website_sale_show_company_data-10.0.1.0.0.99.dev5.dist-info/METADATA
odoo10_addon_website_sale_show_company_data-10.0.1.0.0.99.dev5.dist-info/WHEEL
odoo10_addon_website_sale_show_company_data-10.0.1.0.0.99.dev5.dist-info/namespace_packages.txt
odoo10_addon_website_sale_show_company_data-10.0.1.0.0.99.dev5.dist-info/top_level.txt
odoo10_addon_website_sale_show_company_data-10.0.1.0.0.99.dev5.dist-info/RECORD
